pyBigWig.cpython-37m-x86_64-linux-gnu.so
pyBigWigTest/__init__.py
pyBigWigTest/test.bigBed
pyBigWigTest/test.bw
pyBigWigTest/test.py
pyBigWig-0.3.21.dist-info/LICENSE.txt
pyBigWig-0.3.21.dist-info/WHEEL
pyBigWig-0.3.21.dist-info/top_level.txt
pyBigWig-0.3.21.dist-info/RECORD
pyBigWig-0.3.21.dist-info/METADATA
